alarm_cmd.py
cli.py
simple_alarm.py
scheduler/__init__.py
scheduler/engine.py
scheduler/job_store.py
scheduler/notifications.py
scheduler/recurrence.py
scheduler/runner.py
scheduler/utils.py
scheduler/__pycache__/__init__.cpython-314.pyc
scheduler/__pycache__/engine.cpython-314.pyc
scheduler/__pycache__/job_store.cpython-314.pyc
scheduler/__pycache__/notifications.cpython-314.pyc
scheduler/__pycache__/recurrence.cpython-314.pyc
scheduler/__pycache__/runner.cpython-314.pyc
scheduler/__pycache__/utils.cpython-314.pyc
scheduler_alarms_cli-0.2.1.dist-info/licenses/LICENSE
scheduler_alarms_cli-0.2.1.dist-info/METADATA
scheduler_alarms_cli-0.2.1.dist-info/WHEEL
scheduler_alarms_cli-0.2.1.dist-info/entry_points.txt
scheduler_alarms_cli-0.2.1.dist-info/top_level.txt
scheduler_alarms_cli-0.2.1.dist-info/RECORD
