Metadata-Version: 2.4
Name: scheduler-alarms-cli
Version: 0.2.1
Summary: A simple CLI application to schedule jobs, run tasks, and handle alarms
Home-page: https://github.com/scheduler-alarms/scheduler-alarms-cli
Author: Developer
Author-email: Developer <dev@example.com>
License: MIT
Classifier: Development Status :: 3 - Alpha
Classifier: Intended Audience :: Developers
Classifier: Topic :: Software Development :: Libraries :: Python Modules
Classifier: License :: OSI Approved :: MIT License
Classifier: Programming Language :: Python :: 3
Requires-Python: >=3.7
License-File: LICENSE
Requires-Dist: python-dotenv
Requires-Dist: plyer
Dynamic: author
Dynamic: home-page
Dynamic: license-file
Dynamic: requires-python
